docassemble.ALDashboard-0.25.0-py3.13-nspkg.pth
docassemble/ALDashboard/__init__.py
docassemble/ALDashboard/aldashboard.py
docassemble/ALDashboard/create_package.py
docassemble/ALDashboard/docx_wrangling.py
docassemble/ALDashboard/package_scanner.py
docassemble/ALDashboard/requirements.txt
docassemble/ALDashboard/test_validate_docx.py
docassemble/ALDashboard/translation.py
docassemble/ALDashboard/validate_attachment.py
docassemble/ALDashboard/validate_docx.py
docassemble/ALDashboard/data/questions/api_test.yml
docassemble/ALDashboard/data/questions/browse_interviews.yml
docassemble/ALDashboard/data/questions/compile_bootstrap.yml
docassemble/ALDashboard/data/questions/docx_wrangling.yml
docassemble/ALDashboard/data/questions/generate_translation.yml
docassemble/ALDashboard/data/questions/install_assembly_line.yml
docassemble/ALDashboard/data/questions/install_fonts.yml
docassemble/ALDashboard/data/questions/install_packages.yml
docassemble/ALDashboard/data/questions/list_sessions.yml
docassemble/ALDashboard/data/questions/manage_answer_viewers.yml
docassemble/ALDashboard/data/questions/manage_users.yml
docassemble/ALDashboard/data/questions/menu.yml
docassemble/ALDashboard/data/questions/nav.yml
docassemble/ALDashboard/data/questions/package_scanner.yml
docassemble/ALDashboard/data/questions/pdf_wrangling.yml
docassemble/ALDashboard/data/questions/review_screen_generator.yml
docassemble/ALDashboard/data/questions/test_translate_fragments.yml
docassemble/ALDashboard/data/questions/update_packages.yml
docassemble/ALDashboard/data/questions/validate_attachment.yml
docassemble/ALDashboard/data/questions/validate_docx.yml
docassemble/ALDashboard/data/questions/validate_translation.yml
docassemble/ALDashboard/data/sources/README.md
docassemble/ALDashboard/data/static/README.md
docassemble/ALDashboard/data/static/al_dashboard.css
docassemble/ALDashboard/data/static/bootstrap.svg
docassemble/ALDashboard/data/static/test_html.html
docassemble_aldashboard-0.25.0.dist-info/licenses/LICENSE
docassemble_aldashboard-0.25.0.dist-info/METADATA
docassemble_aldashboard-0.25.0.dist-info/WHEEL
docassemble_aldashboard-0.25.0.dist-info/namespace_packages.txt
docassemble_aldashboard-0.25.0.dist-info/top_level.txt
docassemble_aldashboard-0.25.0.dist-info/RECORD
