Metadata-Version: 2.4
Name: docassemble.ALDashboard
Version: 0.25.0
Summary: Dashboard for some admin tasks
Home-page: https://github.com/SuffolkLITLab/docassemble-ALDashboard
Author: Quinten Steenhuis
Author-email: qsteenhuis@gmail.com
License: The MIT License (MIT)
License-File: LICENSE
Requires-Dist: PyGithub>=2.1.1
Requires-Dist: docassemble.ALToolbox>=0.9.2
Requires-Dist: python-docx>=1.1.1
Requires-Dist: openai>=1.0
Requires-Dist: tiktoken
Requires-Dist: pyaml
Dynamic: author
Dynamic: author-email
Dynamic: description
Dynamic: description-content-type
Dynamic: home-page
Dynamic: license
Dynamic: license-file
Dynamic: requires-dist
Dynamic: summary
